byted_ray_testbed_manager/__init__.py
byted_ray_testbed_manager-0.0.1.dist-info/METADATA
byted_ray_testbed_manager-0.0.1.dist-info/WHEEL
byted_ray_testbed_manager-0.0.1.dist-info/top_level.txt
byted_ray_testbed_manager-0.0.1.dist-info/RECORD
