Metadata-Version: 2.1
Name: byted-ray-testbed-manager
Version: 0.0.1
Summary: A simple package named byted_ray_testbed_manager
Home-page: https://github.com/artifact/byted_ray_testbed_manager.git
Author: artifact
Author-email: artifact@example.com
License: UNKNOWN
Platform: UNKNOWN
Classifier: Programming Language :: Python :: 3
Classifier: License :: OSI Approved :: MIT License
Classifier: Operating System :: OS Independent
